[
  {
    "created_at": "Thu Jun 22 19:31:38 +0000 2017",
    "id": 877972364499206144,
    "id_str": "877972364499206144",
    "text": "@Goncalojr93 Curte fazer um tweet em",
    "truncated": false,
    "entities": {
      "hashtags": [],
      "symbols": [],
      "user_mentions": [
        {
          "screen_name": "Goncalojr93",
          "name": "Gonçalo lima",
          "id": 129070750,
          "id_str": "129070750",
          "indices": [
            0,
            12
          ]
        }
      ],
      "urls": []
    },
    "source": "<a href=\"http://twitter.com/download/android\" rel=\"nofollow\">Twitter for Android</a>",
    "in_reply_to_status_id": 877972085363978240,
    "in_reply_to_status_id_str": "877972085363978240",
    "in_reply_to_user_id": 129070750,
    "in_reply_to_user_id_str": "129070750",
    "in_reply_to_screen_name": "Goncalojr93",
    "user": {
      "id": 290283024,
      "id_str": "290283024",
      "name": "Ezequiel",
      "screen_name": "ZicaMessore",
      "location": "",
      "description": "",
      "url": null,
      "entities": {
        "description": {
          "urls": []
        }
      },
      "protected": false,
      "followers_count": 40,
      "friends_count": 139,
      "listed_count": 0,
      "created_at": "Sat Apr 30 01:29:24 +0000 2011",
      "favourites_count": 2,
      "utc_offset": null,
      "time_zone": null,
      "geo_enabled": true,
      "verified": false,
      "statuses_count": 21,
      "lang": "pt",
      "contributors_enabled": false,
      "is_translator": false,
      "is_translation_enabled": false,
      "profile_background_color": "642D8B",
      "profile_background_image_url": "http://abs.twimg.com/images/themes/theme10/bg.gif",
      "profile_background_image_url_https": "https://abs.twimg.com/images/themes/theme10/bg.gif",
      "profile_background_tile": true,
      "profile_image_url": "http://pbs.twimg.com/profile_images/838732277140062213/6HvND1Iy_normal.jpg",
      "profile_image_url_https": "https://pbs.twimg.com/profile_images/838732277140062213/6HvND1Iy_normal.jpg",
      "profile_link_color": "FF0000",
      "profile_sidebar_border_color": "65B0DA",
      "profile_sidebar_fill_color": "7AC3EE",
      "profile_text_color": "3D1957",
      "profile_use_background_image": true,
      "has_extended_profile": false,
      "default_profile": false,
      "default_profile_image": false,
      "following": null,
      "follow_request_sent": null,
      "notifications": null,
      "translator_type": "none"
    },
    "geo": null,
    "coordinates": null,
    "place": null,
    "contributors": null,
    "is_quote_status": false,
    "retweet_count": 0,
    "favorite_count": 0,
    "favorited": false,
    "retweeted": false,
    "lang": "pt"
  },
  {
    "created_at": "Sat May 27 22:50:39 +0000 2017",
    "id": 868600366459482112,
    "id_str": "868600366459482112",
    "text": "Infelizmente acabou mais foi bom de mais parabéns a todos os organizadores esperamos por mais eventos fantásticos igual a esse\n#DevConf2017",
    "truncated": false,
    "entities": {
      "hashtags": [
        {
          "text": "DevConf2017",
          "indices": [
            127,
            139
          ]
        }
      ],
      "symbols": [],
      "user_mentions": [],
      "urls": []
    },
    "source": "<a href=\"http://twitter.com/download/android\" rel=\"nofollow\">Twitter for Android</a>",
    "in_reply_to_status_id": null,
    "in_reply_to_status_id_str": null,
    "in_reply_to_user_id": null,
    "in_reply_to_user_id_str": null,
    "in_reply_to_screen_name": null,
    "user": {
      "id": 290283024,
      "id_str": "290283024",
      "name": "Ezequiel",
      "screen_name": "ZicaMessore",
      "location": "",
      "description": "",
      "url": null,
      "entities": {
        "description": {
          "urls": []
        }
      },
      "protected": false,
      "followers_count": 40,
      "friends_count": 139,
      "listed_count": 0,
      "created_at": "Sat Apr 30 01:29:24 +0000 2011",
      "favourites_count": 2,
      "utc_offset": null,
      "time_zone": null,
      "geo_enabled": true,
      "verified": false,
      "statuses_count": 21,
      "lang": "pt",
      "contributors_enabled": false,
      "is_translator": false,
      "is_translation_enabled": false,
      "profile_background_color": "642D8B",
      "profile_background_image_url": "http://abs.twimg.com/images/themes/theme10/bg.gif",
      "profile_background_image_url_https": "https://abs.twimg.com/images/themes/theme10/bg.gif",
      "profile_background_tile": true,
      "profile_image_url": "http://pbs.twimg.com/profile_images/838732277140062213/6HvND1Iy_normal.jpg",
      "profile_image_url_https": "https://pbs.twimg.com/profile_images/838732277140062213/6HvND1Iy_normal.jpg",
      "profile_link_color": "FF0000",
      "profile_sidebar_border_color": "65B0DA",
      "profile_sidebar_fill_color": "7AC3EE",
      "profile_text_color": "3D1957",
      "profile_use_background_image": true,
      "has_extended_profile": false,
      "default_profile": false,
      "default_profile_image": false,
      "following": null,
      "follow_request_sent": null,
      "notifications": null,
      "translator_type": "none"
    },
    "geo": null,
    "coordinates": null,
    "place": {
      "id": "07d9cab91ec81002",
      "url": "https://api.twitter.com/1.1/geo/id/07d9cab91ec81002.json",
      "place_type": "poi",
      "name": "Anfiteatro Bento Prado Jr.",
      "full_name": "Anfiteatro Bento Prado Jr.",
      "country_code": "BR",
      "country": "Brasil",
      "contained_within": [],
      "bounding_box": {
        "type": "Polygon",
        "coordinates": [
          [
            [
              -47.88168838824584,
              -21.98364259506933
            ],
            [
              -47.88168838824584,
              -21.98364259506933
            ],
            [
              -47.88168838824584,
              -21.98364259506933
            ],
            [
              -47.88168838824584,
              -21.98364259506933
            ]
          ]
        ]
      },
      "attributes": {}
    },
    "contributors": null,
    "is_quote_status": false,
    "retweet_count": 0,
    "favorite_count": 0,
    "favorited": false,
    "retweeted": false,
    "lang": "pt"
  },
  {
    "created_at": "Sat May 27 12:00:26 +0000 2017",
    "id": 868436730873098240,
    "id_str": "868436730873098240",
    "text": "Gogo primeira palestra Docker para desenvolvedores ...\n#DevConf2017",
    "truncated": false,
    "entities": {
      "hashtags": [
        {
          "text": "DevConf2017",
          "indices": [
            55,
            67
          ]
        }
      ],
      "symbols": [],
      "user_mentions": [],
      "urls": []
    },
    "source": "<a href=\"http://twitter.com/download/android\" rel=\"nofollow\">Twitter for Android</a>",
    "in_reply_to_status_id": null,
    "in_reply_to_status_id_str": null,
    "in_reply_to_user_id": null,
    "in_reply_to_user_id_str": null,
    "in_reply_to_screen_name": null,
    "user": {
      "id": 290283024,
      "id_str": "290283024",
      "name": "Ezequiel",
      "screen_name": "ZicaMessore",
      "location": "",
      "description": "",
      "url": null,
      "entities": {
        "description": {
          "urls": []
        }
      },
      "protected": false,
      "followers_count": 40,
      "friends_count": 139,
      "listed_count": 0,
      "created_at": "Sat Apr 30 01:29:24 +0000 2011",
      "favourites_count": 2,
      "utc_offset": null,
      "time_zone": null,
      "geo_enabled": true,
      "verified": false,
      "statuses_count": 21,
      "lang": "pt",
      "contributors_enabled": false,
      "is_translator": false,
      "is_translation_enabled": false,
      "profile_background_color": "642D8B",
      "profile_background_image_url": "http://abs.twimg.com/images/themes/theme10/bg.gif",
      "profile_background_image_url_https": "https://abs.twimg.com/images/themes/theme10/bg.gif",
      "profile_background_tile": true,
      "profile_image_url": "http://pbs.twimg.com/profile_images/838732277140062213/6HvND1Iy_normal.jpg",
      "profile_image_url_https": "https://pbs.twimg.com/profile_images/838732277140062213/6HvND1Iy_normal.jpg",
      "profile_link_color": "FF0000",
      "profile_sidebar_border_color": "65B0DA",
      "profile_sidebar_fill_color": "7AC3EE",
      "profile_text_color": "3D1957",
      "profile_use_background_image": true,
      "has_extended_profile": false,
      "default_profile": false,
      "default_profile_image": false,
      "following": null,
      "follow_request_sent": null,
      "notifications": null,
      "translator_type": "none"
    },
    "geo": null,
    "coordinates": null,
    "place": null,
    "contributors": null,
    "is_quote_status": false,
    "retweet_count": 0,
    "favorite_count": 3,
    "favorited": false,
    "retweeted": false,
    "lang": "pt"
  },
  {
    "created_at": "Fri Apr 10 16:02:39 +0000 2015",
    "id": 586559927742812160,
    "id_str": "586559927742812160",
    "text": "RT @programafe: Você tem que ser um confrontador. http://t.co/0khC9vEvGL",
    "truncated": false,
    "entities": {
      "hashtags": [],
      "symbols": [],
      "user_mentions": [
        {
          "screen_name": "programafe",
          "name": "Programa Fé",
          "id": 712804921,
          "id_str": "712804921",
          "indices": [
            3,
            14
          ]
        }
      ],
      "urls": [
        {
          "url": "http://t.co/0khC9vEvGL",
          "expanded_url": "http://bit.ly/1NeeEi7",
          "display_url": "bit.ly/1NeeEi7",
          "indices": [
            50,
            72
          ]
        }
      ]
    },
    "source": "<a href=\"http://twitter.com\" rel=\"nofollow\">Twitter Web Client</a>",
    "in_reply_to_status_id": null,
    "in_reply_to_status_id_str": null,
    "in_reply_to_user_id": null,
    "in_reply_to_user_id_str": null,
    "in_reply_to_screen_name": null,
    "user": {
      "id": 290283024,
      "id_str": "290283024",
      "name": "Ezequiel",
      "screen_name": "ZicaMessore",
      "location": "",
      "description": "",
      "url": null,
      "entities": {
        "description": {
          "urls": []
        }
      },
      "protected": false,
      "followers_count": 40,
      "friends_count": 139,
      "listed_count": 0,
      "created_at": "Sat Apr 30 01:29:24 +0000 2011",
      "favourites_count": 2,
      "utc_offset": null,
      "time_zone": null,
      "geo_enabled": true,
      "verified": false,
      "statuses_count": 21,
      "lang": "pt",
      "contributors_enabled": false,
      "is_translator": false,
      "is_translation_enabled": false,
      "profile_background_color": "642D8B",
      "profile_background_image_url": "http://abs.twimg.com/images/themes/theme10/bg.gif",
      "profile_background_image_url_https": "https://abs.twimg.com/images/themes/theme10/bg.gif",
      "profile_background_tile": true,
      "profile_image_url": "http://pbs.twimg.com/profile_images/838732277140062213/6HvND1Iy_normal.jpg",
      "profile_image_url_https": "https://pbs.twimg.com/profile_images/838732277140062213/6HvND1Iy_normal.jpg",
      "profile_link_color": "FF0000",
      "profile_sidebar_border_color": "65B0DA",
      "profile_sidebar_fill_color": "7AC3EE",
      "profile_text_color": "3D1957",
      "profile_use_background_image": true,
      "has_extended_profile": false,
      "default_profile": false,
      "default_profile_image": false,
      "following": null,
      "follow_request_sent": null,
      "notifications": null,
      "translator_type": "none"
    },
    "geo": null,
    "coordinates": null,
    "place": null,
    "contributors": null,
    "retweeted_status": {
      "created_at": "Thu Apr 09 12:42:36 +0000 2015",
      "id": 586147196627738624,
      "id_str": "586147196627738624",
      "text": "Você tem que ser um confrontador. http://t.co/0khC9vEvGL",
      "truncated": false,
      "entities": {
        "hashtags": [],
        "symbols": [],
        "user_mentions": [],
        "urls": [
          {
            "url": "http://t.co/0khC9vEvGL",
            "expanded_url": "http://bit.ly/1NeeEi7",
            "display_url": "bit.ly/1NeeEi7",
            "indices": [
              34,
              56
            ]
          }
        ]
      },
      "source": "<a href=\"https://about.twitter.com/products/tweetdeck\" rel=\"nofollow\">TweetDeck</a>",
      "in_reply_to_status_id": null,
      "in_reply_to_status_id_str": null,
      "in_reply_to_user_id": null,
      "in_reply_to_user_id_str": null,
      "in_reply_to_screen_name": null,
      "user": {
        "id": 712804921,
        "id_str": "712804921",
        "name": "Programa Fé",
        "screen_name": "programafe",
        "location": "",
        "description": "Programa da REDE SUPER. Apresentação: @andrevaladao. Músicas, mensagens e os bastidores da turnê do cantor.",
        "url": "http://t.co/PVs4ArqLAG",
        "entities": {
          "url": {
            "urls": [
              {
                "url": "http://t.co/PVs4ArqLAG",
                "expanded_url": "http://redesper.com.br/fe",
                "display_url": "redesper.com.br/fe",
                "indices": [
                  0,
                  22
                ]
              }
            ]
          },
          "description": {
            "urls": []
          }
        },
        "protected": false,
        "followers_count": 9857,
        "friends_count": 43,
        "listed_count": 4,
        "created_at": "Mon Jul 23 17:39:10 +0000 2012",
        "favourites_count": 620,
        "utc_offset": null,
        "time_zone": null,
        "geo_enabled": false,
        "verified": false,
        "statuses_count": 957,
        "lang": "pt",
        "contributors_enabled": false,
        "is_translator": false,
        "is_translation_enabled": false,
        "profile_background_color": "C0DEED",
        "profile_background_image_url": "http://abs.twimg.com/images/themes/theme1/bg.png",
        "profile_background_image_url_https": "https://abs.twimg.com/images/themes/theme1/bg.png",
        "profile_background_tile": false,
        "profile_image_url": "http://pbs.twimg.com/profile_images/844586931300290561/Fk_7M9eY_normal.jpg",
        "profile_image_url_https": "https://pbs.twimg.com/profile_images/844586931300290561/Fk_7M9eY_normal.jpg",
        "profile_banner_url": "https://pbs.twimg.com/profile_banners/712804921/1490203499",
        "profile_link_color": "0084B4",
        "profile_sidebar_border_color": "C0DEED",
        "profile_sidebar_fill_color": "DDEEF6",
        "profile_text_color": "333333",
        "profile_use_background_image": true,
        "has_extended_profile": false,
        "default_profile": false,
        "default_profile_image": false,
        "following": null,
        "follow_request_sent": null,
        "notifications": null,
        "translator_type": "none"
      },
      "geo": null,
      "coordinates": null,
      "place": null,
      "contributors": null,
      "is_quote_status": false,
      "retweet_count": 4,
      "favorite_count": 8,
      "favorited": false,
      "retweeted": false,
      "possibly_sensitive": false,
      "lang": "pt"
    },
    "is_quote_status": false,
    "retweet_count": 4,
    "favorite_count": 0,
    "favorited": false,
    "retweeted": false,
    "possibly_sensitive": false,
    "lang": "pt"
  },
  {
    "created_at": "Wed Nov 21 20:19:22 +0000 2012",
    "id": 271347090049871872,
    "id_str": "271347090049871872",
    "text": "@vccomenta aa Tem simm ... Fantasi da Champion eh muito legal ... Soh q naum como nosso cartola ...",
    "truncated": false,
    "entities": {
      "hashtags": [],
      "symbols": [],
      "user_mentions": [
        {
          "screen_name": "vccomenta",
          "name": "vccomenta",
          "id": 95726236,
          "id_str": "95726236",
          "indices": [
            0,
            10
          ]
        }
      ],
      "urls": []
    },
    "source": "<a href=\"http://twitter.com\" rel=\"nofollow\">Twitter Web Client</a>",
    "in_reply_to_status_id": null,
    "in_reply_to_status_id_str": null,
    "in_reply_to_user_id": 95726236,
    "in_reply_to_user_id_str": "95726236",
    "in_reply_to_screen_name": "vccomenta",
    "user": {
      "id": 290283024,
      "id_str": "290283024",
      "name": "Ezequiel",
      "screen_name": "ZicaMessore",
      "location": "",
      "description": "",
      "url": null,
      "entities": {
        "description": {
          "urls": []
        }
      },
      "protected": false,
      "followers_count": 40,
      "friends_count": 139,
      "listed_count": 0,
      "created_at": "Sat Apr 30 01:29:24 +0000 2011",
      "favourites_count": 2,
      "utc_offset": null,
      "time_zone": null,
      "geo_enabled": true,
      "verified": false,
      "statuses_count": 21,
      "lang": "pt",
      "contributors_enabled": false,
      "is_translator": false,
      "is_translation_enabled": false,
      "profile_background_color": "642D8B",
      "profile_background_image_url": "http://abs.twimg.com/images/themes/theme10/bg.gif",
      "profile_background_image_url_https": "https://abs.twimg.com/images/themes/theme10/bg.gif",
      "profile_background_tile": true,
      "profile_image_url": "http://pbs.twimg.com/profile_images/838732277140062213/6HvND1Iy_normal.jpg",
      "profile_image_url_https": "https://pbs.twimg.com/profile_images/838732277140062213/6HvND1Iy_normal.jpg",
      "profile_link_color": "FF0000",
      "profile_sidebar_border_color": "65B0DA",
      "profile_sidebar_fill_color": "7AC3EE",
      "profile_text_color": "3D1957",
      "profile_use_background_image": true,
      "has_extended_profile": false,
      "default_profile": false,
      "default_profile_image": false,
      "following": null,
      "follow_request_sent": null,
      "notifications": null,
      "translator_type": "none"
    },
    "geo": null,
    "coordinates": null,
    "place": null,
    "contributors": null,
    "is_quote_status": false,
    "retweet_count": 0,
    "favorite_count": 0,
    "favorited": false,
    "retweeted": false,
    "lang": "pt"
  },
  {
    "created_at": "Thu Apr 12 10:38:55 +0000 2012",
    "id": 190388519993229312,
    "id_str": "190388519993229312",
    "text": "Wow. Everyone should check out ad-free #radio with gorgeous band photos and social features. Great music. http://t.co/5JXJkoZr via @earbits",
    "truncated": false,
    "entities": {
      "hashtags": [
        {
          "text": "radio",
          "indices": [
            39,
            45
          ]
        }
      ],
      "symbols": [],
      "user_mentions": [
        {
          "screen_name": "earbits",
          "name": "Earbits Radio",
          "id": 112833256,
          "id_str": "112833256",
          "indices": [
            131,
            139
          ]
        }
      ],
      "urls": [
        {
          "url": "http://t.co/5JXJkoZr",
          "expanded_url": "http://earbits.com",
          "display_url": "earbits.com",
          "indices": [
            106,
            126
          ]
        }
      ]
    },
    "source": "<a href=\"https://dev.twitter.com/docs/tfw\" rel=\"nofollow\">Twitter for Websites</a>",
    "in_reply_to_status_id": null,
    "in_reply_to_status_id_str": null,
    "in_reply_to_user_id": null,
    "in_reply_to_user_id_str": null,
    "in_reply_to_screen_name": null,
    "user": {
      "id": 290283024,
      "id_str": "290283024",
      "name": "Ezequiel",
      "screen_name": "ZicaMessore",
      "location": "",
      "description": "",
      "url": null,
      "entities": {
        "description": {
          "urls": []
        }
      },
      "protected": false,
      "followers_count": 40,
      "friends_count": 139,
      "listed_count": 0,
      "created_at": "Sat Apr 30 01:29:24 +0000 2011",
      "favourites_count": 2,
      "utc_offset": null,
      "time_zone": null,
      "geo_enabled": true,
      "verified": false,
      "statuses_count": 21,
      "lang": "pt",
      "contributors_enabled": false,
      "is_translator": false,
      "is_translation_enabled": false,
      "profile_background_color": "642D8B",
      "profile_background_image_url": "http://abs.twimg.com/images/themes/theme10/bg.gif",
      "profile_background_image_url_https": "https://abs.twimg.com/images/themes/theme10/bg.gif",
      "profile_background_tile": true,
      "profile_image_url": "http://pbs.twimg.com/profile_images/838732277140062213/6HvND1Iy_normal.jpg",
      "profile_image_url_https": "https://pbs.twimg.com/profile_images/838732277140062213/6HvND1Iy_normal.jpg",
      "profile_link_color": "FF0000",
      "profile_sidebar_border_color": "65B0DA",
      "profile_sidebar_fill_color": "7AC3EE",
      "profile_text_color": "3D1957",
      "profile_use_background_image": true,
      "has_extended_profile": false,
      "default_profile": false,
      "default_profile_image": false,
      "following": null,
      "follow_request_sent": null,
      "notifications": null,
      "translator_type": "none"
    },
    "geo": null,
    "coordinates": null,
    "place": null,
    "contributors": null,
    "is_quote_status": false,
    "retweet_count": 0,
    "favorite_count": 0,
    "favorited": false,
    "retweeted": false,
    "possibly_sensitive": false,
    "lang": "en"
  },
  {
    "created_at": "Fri Dec 02 12:17:09 +0000 2011",
    "id": 142578046086545408,
    "id_str": "142578046086545408",
    "text": "♫ #Escutando Katy Perry - The One That Got Away no #MeuVagalume #MusicFriday http://t.co/y8L9gMV5",
    "truncated": false,
    "entities": {
      "hashtags": [
        {
          "text": "Escutando",
          "indices": [
            2,
            12
          ]
        },
        {
          "text": "MeuVagalume",
          "indices": [
            51,
            63
          ]
        },
        {
          "text": "MusicFriday",
          "indices": [
            64,
            76
          ]
        }
      ],
      "symbols": [],
      "user_mentions": [],
      "urls": [
        {
          "url": "http://t.co/y8L9gMV5",
          "expanded_url": "http://vagalu.me/sitevagalume/1527587/47825163/",
          "display_url": "vagalu.me/sitevagalume/1…",
          "indices": [
            77,
            97
          ]
        }
      ]
    },
    "source": "<a href=\"https://dev.twitter.com/docs/tfw\" rel=\"nofollow\">Twitter for Websites</a>",
    "in_reply_to_status_id": null,
    "in_reply_to_status_id_str": null,
    "in_reply_to_user_id": null,
    "in_reply_to_user_id_str": null,
    "in_reply_to_screen_name": null,
    "user": {
      "id": 290283024,
      "id_str": "290283024",
      "name": "Ezequiel",
      "screen_name": "ZicaMessore",
      "location": "",
      "description": "",
      "url": null,
      "entities": {
        "description": {
          "urls": []
        }
      },
      "protected": false,
      "followers_count": 40,
      "friends_count": 139,
      "listed_count": 0,
      "created_at": "Sat Apr 30 01:29:24 +0000 2011",
      "favourites_count": 2,
      "utc_offset": null,
      "time_zone": null,
      "geo_enabled": true,
      "verified": false,
      "statuses_count": 21,
      "lang": "pt",
      "contributors_enabled": false,
      "is_translator": false,
      "is_translation_enabled": false,
      "profile_background_color": "642D8B",
      "profile_background_image_url": "http://abs.twimg.com/images/themes/theme10/bg.gif",
      "profile_background_image_url_https": "https://abs.twimg.com/images/themes/theme10/bg.gif",
      "profile_background_tile": true,
      "profile_image_url": "http://pbs.twimg.com/profile_images/838732277140062213/6HvND1Iy_normal.jpg",
      "profile_image_url_https": "https://pbs.twimg.com/profile_images/838732277140062213/6HvND1Iy_normal.jpg",
      "profile_link_color": "FF0000",
      "profile_sidebar_border_color": "65B0DA",
      "profile_sidebar_fill_color": "7AC3EE",
      "profile_text_color": "3D1957",
      "profile_use_background_image": true,
      "has_extended_profile": false,
      "default_profile": false,
      "default_profile_image": false,
      "following": null,
      "follow_request_sent": null,
      "notifications": null,
      "translator_type": "none"
    },
    "geo": null,
    "coordinates": null,
    "place": null,
    "contributors": null,
    "is_quote_status": false,
    "retweet_count": 0,
    "favorite_count": 0,
    "favorited": false,
    "retweeted": false,
    "possibly_sensitive": false,
    "lang": "en"
  },
  {
    "created_at": "Fri Dec 02 12:11:00 +0000 2011",
    "id": 142576496505139200,
    "id_str": "142576496505139200",
    "text": "@Bah_Pinheiros2 LOka",
    "truncated": false,
    "entities": {
      "hashtags": [],
      "symbols": [],
      "user_mentions": [
        {
          "screen_name": "Bah_Pinheiros2",
          "name": "Bárbara Carneiro ☮",
          "id": 251270485,
          "id_str": "251270485",
          "indices": [
            0,
            15
          ]
        }
      ],
      "urls": []
    },
    "source": "<a href=\"http://twitter.com\" rel=\"nofollow\">Twitter Web Client</a>",
    "in_reply_to_status_id": 142576351222824960,
    "in_reply_to_status_id_str": "142576351222824960",
    "in_reply_to_user_id": 251270485,
    "in_reply_to_user_id_str": "251270485",
    "in_reply_to_screen_name": "Bah_Pinheiros2",
    "user": {
      "id": 290283024,
      "id_str": "290283024",
      "name": "Ezequiel",
      "screen_name": "ZicaMessore",
      "location": "",
      "description": "",
      "url": null,
      "entities": {
        "description": {
          "urls": []
        }
      },
      "protected": false,
      "followers_count": 40,
      "friends_count": 139,
      "listed_count": 0,
      "created_at": "Sat Apr 30 01:29:24 +0000 2011",
      "favourites_count": 2,
      "utc_offset": null,
      "time_zone": null,
      "geo_enabled": true,
      "verified": false,
      "statuses_count": 21,
      "lang": "pt",
      "contributors_enabled": false,
      "is_translator": false,
      "is_translation_enabled": false,
      "profile_background_color": "642D8B",
      "profile_background_image_url": "http://abs.twimg.com/images/themes/theme10/bg.gif",
      "profile_background_image_url_https": "https://abs.twimg.com/images/themes/theme10/bg.gif",
      "profile_background_tile": true,
      "profile_image_url": "http://pbs.twimg.com/profile_images/838732277140062213/6HvND1Iy_normal.jpg",
      "profile_image_url_https": "https://pbs.twimg.com/profile_images/838732277140062213/6HvND1Iy_normal.jpg",
      "profile_link_color": "FF0000",
      "profile_sidebar_border_color": "65B0DA",
      "profile_sidebar_fill_color": "7AC3EE",
      "profile_text_color": "3D1957",
      "profile_use_background_image": true,
      "has_extended_profile": false,
      "default_profile": false,
      "default_profile_image": false,
      "following": null,
      "follow_request_sent": null,
      "notifications": null,
      "translator_type": "none"
    },
    "geo": null,
    "coordinates": null,
    "place": null,
    "contributors": null,
    "is_quote_status": false,
    "retweet_count": 0,
    "favorite_count": 0,
    "favorited": false,
    "retweeted": false,
    "lang": "is"
  },
  {
    "created_at": "Fri Dec 02 12:10:36 +0000 2011",
    "id": 142576396307415040,
    "id_str": "142576396307415040",
    "text": "Aoo Semana q Num acaBa ... Vem ne mim FDS",
    "truncated": false,
    "entities": {
      "hashtags": [],
      "symbols": [],
      "user_mentions": [],
      "urls": []
    },
    "source": "<a href=\"http://twitter.com\" rel=\"nofollow\">Twitter Web Client</a>",
    "in_reply_to_status_id": null,
    "in_reply_to_status_id_str": null,
    "in_reply_to_user_id": null,
    "in_reply_to_user_id_str": null,
    "in_reply_to_screen_name": null,
    "user": {
      "id": 290283024,
      "id_str": "290283024",
      "name": "Ezequiel",
      "screen_name": "ZicaMessore",
      "location": "",
      "description": "",
      "url": null,
      "entities": {
        "description": {
          "urls": []
        }
      },
      "protected": false,
      "followers_count": 40,
      "friends_count": 139,
      "listed_count": 0,
      "created_at": "Sat Apr 30 01:29:24 +0000 2011",
      "favourites_count": 2,
      "utc_offset": null,
      "time_zone": null,
      "geo_enabled": true,
      "verified": false,
      "statuses_count": 21,
      "lang": "pt",
      "contributors_enabled": false,
      "is_translator": false,
      "is_translation_enabled": false,
      "profile_background_color": "642D8B",
      "profile_background_image_url": "http://abs.twimg.com/images/themes/theme10/bg.gif",
      "profile_background_image_url_https": "https://abs.twimg.com/images/themes/theme10/bg.gif",
      "profile_background_tile": true,
      "profile_image_url": "http://pbs.twimg.com/profile_images/838732277140062213/6HvND1Iy_normal.jpg",
      "profile_image_url_https": "https://pbs.twimg.com/profile_images/838732277140062213/6HvND1Iy_normal.jpg",
      "profile_link_color": "FF0000",
      "profile_sidebar_border_color": "65B0DA",
      "profile_sidebar_fill_color": "7AC3EE",
      "profile_text_color": "3D1957",
      "profile_use_background_image": true,
      "has_extended_profile": false,
      "default_profile": false,
      "default_profile_image": false,
      "following": null,
      "follow_request_sent": null,
      "notifications": null,
      "translator_type": "none"
    },
    "geo": null,
    "coordinates": null,
    "place": null,
    "contributors": null,
    "is_quote_status": false,
    "retweet_count": 0,
    "favorite_count": 0,
    "favorited": false,
    "retweeted": false,
    "lang": "pt"
  },
  {
    "created_at": "Sun Nov 20 20:58:42 +0000 2011",
    "id": 138360644499021825,
    "id_str": "138360644499021825",
    "text": "eh Vasco Penso q Ia se Lider  Nem Pauu ....",
    "truncated": false,
    "entities": {
      "hashtags": [],
      "symbols": [],
      "user_mentions": [],
      "urls": []
    },
    "source": "<a href=\"http://twitter.com\" rel=\"nofollow\">Twitter Web Client</a>",
    "in_reply_to_status_id": null,
    "in_reply_to_status_id_str": null,
    "in_reply_to_user_id": null,
    "in_reply_to_user_id_str": null,
    "in_reply_to_screen_name": null,
    "user": {
      "id": 290283024,
      "id_str": "290283024",
      "name": "Ezequiel",
      "screen_name": "ZicaMessore",
      "location": "",
      "description": "",
      "url": null,
      "entities": {
        "description": {
          "urls": []
        }
      },
      "protected": false,
      "followers_count": 40,
      "friends_count": 139,
      "listed_count": 0,
      "created_at": "Sat Apr 30 01:29:24 +0000 2011",
      "favourites_count": 2,
      "utc_offset": null,
      "time_zone": null,
      "geo_enabled": true,
      "verified": false,
      "statuses_count": 21,
      "lang": "pt",
      "contributors_enabled": false,
      "is_translator": false,
      "is_translation_enabled": false,
      "profile_background_color": "642D8B",
      "profile_background_image_url": "http://abs.twimg.com/images/themes/theme10/bg.gif",
      "profile_background_image_url_https": "https://abs.twimg.com/images/themes/theme10/bg.gif",
      "profile_background_tile": true,
      "profile_image_url": "http://pbs.twimg.com/profile_images/838732277140062213/6HvND1Iy_normal.jpg",
      "profile_image_url_https": "https://pbs.twimg.com/profile_images/838732277140062213/6HvND1Iy_normal.jpg",
      "profile_link_color": "FF0000",
      "profile_sidebar_border_color": "65B0DA",
      "profile_sidebar_fill_color": "7AC3EE",
      "profile_text_color": "3D1957",
      "profile_use_background_image": true,
      "has_extended_profile": false,
      "default_profile": false,
      "default_profile_image": false,
      "following": null,
      "follow_request_sent": null,
      "notifications": null,
      "translator_type": "none"
    },
    "geo": null,
    "coordinates": null,
    "place": null,
    "contributors": null,
    "is_quote_status": false,
    "retweet_count": 0,
    "favorite_count": 0,
    "favorited": false,
    "retweeted": false,
    "lang": "pt"
  },
  {
    "created_at": "Sun Nov 20 20:56:12 +0000 2011",
    "id": 138360012887175168,
    "id_str": "138360012887175168",
    "text": "Aq Tem Um BanDo De LOkos  ....",
    "truncated": false,
    "entities": {
      "hashtags": [],
      "symbols": [],
      "user_mentions": [],
      "urls": []
    },
    "source": "<a href=\"http://twitter.com\" rel=\"nofollow\">Twitter Web Client</a>",
    "in_reply_to_status_id": null,
    "in_reply_to_status_id_str": null,
    "in_reply_to_user_id": null,
    "in_reply_to_user_id_str": null,
    "in_reply_to_screen_name": null,
    "user": {
      "id": 290283024,
      "id_str": "290283024",
      "name": "Ezequiel",
      "screen_name": "ZicaMessore",
      "location": "",
      "description": "",
      "url": null,
      "entities": {
        "description": {
          "urls": []
        }
      },
      "protected": false,
      "followers_count": 40,
      "friends_count": 139,
      "listed_count": 0,
      "created_at": "Sat Apr 30 01:29:24 +0000 2011",
      "favourites_count": 2,
      "utc_offset": null,
      "time_zone": null,
      "geo_enabled": true,
      "verified": false,
      "statuses_count": 21,
      "lang": "pt",
      "contributors_enabled": false,
      "is_translator": false,
      "is_translation_enabled": false,
      "profile_background_color": "642D8B",
      "profile_background_image_url": "http://abs.twimg.com/images/themes/theme10/bg.gif",
      "profile_background_image_url_https": "https://abs.twimg.com/images/themes/theme10/bg.gif",
      "profile_background_tile": true,
      "profile_image_url": "http://pbs.twimg.com/profile_images/838732277140062213/6HvND1Iy_normal.jpg",
      "profile_image_url_https": "https://pbs.twimg.com/profile_images/838732277140062213/6HvND1Iy_normal.jpg",
      "profile_link_color": "FF0000",
      "profile_sidebar_border_color": "65B0DA",
      "profile_sidebar_fill_color": "7AC3EE",
      "profile_text_color": "3D1957",
      "profile_use_background_image": true,
      "has_extended_profile": false,
      "default_profile": false,
      "default_profile_image": false,
      "following": null,
      "follow_request_sent": null,
      "notifications": null,
      "translator_type": "none"
    },
    "geo": null,
    "coordinates": null,
    "place": null,
    "contributors": null,
    "is_quote_status": false,
    "retweet_count": 0,
    "favorite_count": 0,
    "favorited": false,
    "retweeted": false,
    "lang": "pt"
  },
  {
    "created_at": "Sun Nov 20 20:53:12 +0000 2011",
    "id": 138359259829248001,
    "id_str": "138359259829248001",
    "text": "Ta eh Imperador .... PORRA",
    "truncated": false,
    "entities": {
      "hashtags": [],
      "symbols": [],
      "user_mentions": [],
      "urls": []
    },
    "source": "<a href=\"http://twitter.com\" rel=\"nofollow\">Twitter Web Client</a>",
    "in_reply_to_status_id": null,
    "in_reply_to_status_id_str": null,
    "in_reply_to_user_id": null,
    "in_reply_to_user_id_str": null,
    "in_reply_to_screen_name": null,
    "user": {
      "id": 290283024,
      "id_str": "290283024",
      "name": "Ezequiel",
      "screen_name": "ZicaMessore",
      "location": "",
      "description": "",
      "url": null,
      "entities": {
        "description": {
          "urls": []
        }
      },
      "protected": false,
      "followers_count": 40,
      "friends_count": 139,
      "listed_count": 0,
      "created_at": "Sat Apr 30 01:29:24 +0000 2011",
      "favourites_count": 2,
      "utc_offset": null,
      "time_zone": null,
      "geo_enabled": true,
      "verified": false,
      "statuses_count": 21,
      "lang": "pt",
      "contributors_enabled": false,
      "is_translator": false,
      "is_translation_enabled": false,
      "profile_background_color": "642D8B",
      "profile_background_image_url": "http://abs.twimg.com/images/themes/theme10/bg.gif",
      "profile_background_image_url_https": "https://abs.twimg.com/images/themes/theme10/bg.gif",
      "profile_background_tile": true,
      "profile_image_url": "http://pbs.twimg.com/profile_images/838732277140062213/6HvND1Iy_normal.jpg",
      "profile_image_url_https": "https://pbs.twimg.com/profile_images/838732277140062213/6HvND1Iy_normal.jpg",
      "profile_link_color": "FF0000",
      "profile_sidebar_border_color": "65B0DA",
      "profile_sidebar_fill_color": "7AC3EE",
      "profile_text_color": "3D1957",
      "profile_use_background_image": true,
      "has_extended_profile": false,
      "default_profile": false,
      "default_profile_image": false,
      "following": null,
      "follow_request_sent": null,
      "notifications": null,
      "translator_type": "none"
    },
    "geo": null,
    "coordinates": null,
    "place": null,
    "contributors": null,
    "is_quote_status": false,
    "retweet_count": 0,
    "favorite_count": 0,
    "favorited": false,
    "retweeted": false,
    "lang": "es"
  },
  {
    "created_at": "Fri Nov 18 00:37:09 +0000 2011",
    "id": 137328454432591872,
    "id_str": "137328454432591872",
    "text": "Saindo Aq Daq a Poco ... SaGa Crepusculo - AManhecer ....PARTIU##",
    "truncated": false,
    "entities": {
      "hashtags": [],
      "symbols": [],
      "user_mentions": [],
      "urls": []
    },
    "source": "<a href=\"http://twitter.com\" rel=\"nofollow\">Twitter Web Client</a>",
    "in_reply_to_status_id": null,
    "in_reply_to_status_id_str": null,
    "in_reply_to_user_id": null,
    "in_reply_to_user_id_str": null,
    "in_reply_to_screen_name": null,
    "user": {
      "id": 290283024,
      "id_str": "290283024",
      "name": "Ezequiel",
      "screen_name": "ZicaMessore",
      "location": "",
      "description": "",
      "url": null,
      "entities": {
        "description": {
          "urls": []
        }
      },
      "protected": false,
      "followers_count": 40,
      "friends_count": 139,
      "listed_count": 0,
      "created_at": "Sat Apr 30 01:29:24 +0000 2011",
      "favourites_count": 2,
      "utc_offset": null,
      "time_zone": null,
      "geo_enabled": true,
      "verified": false,
      "statuses_count": 21,
      "lang": "pt",
      "contributors_enabled": false,
      "is_translator": false,
      "is_translation_enabled": false,
      "profile_background_color": "642D8B",
      "profile_background_image_url": "http://abs.twimg.com/images/themes/theme10/bg.gif",
      "profile_background_image_url_https": "https://abs.twimg.com/images/themes/theme10/bg.gif",
      "profile_background_tile": true,
      "profile_image_url": "http://pbs.twimg.com/profile_images/838732277140062213/6HvND1Iy_normal.jpg",
      "profile_image_url_https": "https://pbs.twimg.com/profile_images/838732277140062213/6HvND1Iy_normal.jpg",
      "profile_link_color": "FF0000",
      "profile_sidebar_border_color": "65B0DA",
      "profile_sidebar_fill_color": "7AC3EE",
      "profile_text_color": "3D1957",
      "profile_use_background_image": true,
      "has_extended_profile": false,
      "default_profile": false,
      "default_profile_image": false,
      "following": null,
      "follow_request_sent": null,
      "notifications": null,
      "translator_type": "none"
    },
    "geo": null,
    "coordinates": null,
    "place": null,
    "contributors": null,
    "is_quote_status": false,
    "retweet_count": 0,
    "favorite_count": 0,
    "favorited": false,
    "retweeted": false,
    "lang": "pt"
  },
  {
    "created_at": "Thu Nov 17 01:55:06 +0000 2011",
    "id": 136985682202734592,
    "id_str": "136985682202734592",
    "text": "Eh Isso Aii Corinthians ... FalTa Poco  ***",
    "truncated": false,
    "entities": {
      "hashtags": [],
      "symbols": [],
      "user_mentions": [],
      "urls": []
    },
    "source": "<a href=\"http://twitter.com\" rel=\"nofollow\">Twitter Web Client</a>",
    "in_reply_to_status_id": null,
    "in_reply_to_status_id_str": null,
    "in_reply_to_user_id": null,
    "in_reply_to_user_id_str": null,
    "in_reply_to_screen_name": null,
    "user": {
      "id": 290283024,
      "id_str": "290283024",
      "name": "Ezequiel",
      "screen_name": "ZicaMessore",
      "location": "",
      "description": "",
      "url": null,
      "entities": {
        "description": {
          "urls": []
        }
      },
      "protected": false,
      "followers_count": 40,
      "friends_count": 139,
      "listed_count": 0,
      "created_at": "Sat Apr 30 01:29:24 +0000 2011",
      "favourites_count": 2,
      "utc_offset": null,
      "time_zone": null,
      "geo_enabled": true,
      "verified": false,
      "statuses_count": 21,
      "lang": "pt",
      "contributors_enabled": false,
      "is_translator": false,
      "is_translation_enabled": false,
      "profile_background_color": "642D8B",
      "profile_background_image_url": "http://abs.twimg.com/images/themes/theme10/bg.gif",
      "profile_background_image_url_https": "https://abs.twimg.com/images/themes/theme10/bg.gif",
      "profile_background_tile": true,
      "profile_image_url": "http://pbs.twimg.com/profile_images/838732277140062213/6HvND1Iy_normal.jpg",
      "profile_image_url_https": "https://pbs.twimg.com/profile_images/838732277140062213/6HvND1Iy_normal.jpg",
      "profile_link_color": "FF0000",
      "profile_sidebar_border_color": "65B0DA",
      "profile_sidebar_fill_color": "7AC3EE",
      "profile_text_color": "3D1957",
      "profile_use_background_image": true,
      "has_extended_profile": false,
      "default_profile": false,
      "default_profile_image": false,
      "following": null,
      "follow_request_sent": null,
      "notifications": null,
      "translator_type": "none"
    },
    "geo": null,
    "coordinates": null,
    "place": null,
    "contributors": null,
    "is_quote_status": false,
    "retweet_count": 0,
    "favorite_count": 0,
    "favorited": false,
    "retweeted": false,
    "lang": "pt"
  },
  {
    "created_at": "Sun Nov 13 19:28:37 +0000 2011",
    "id": 135801259432214528,
    "id_str": "135801259432214528",
    "text": "Acompanhe AO VIVO: Corinthians x Atlético-PR - Campeonato Brasileiro no @globoesportecom #vccomenta http://t.co/zHijqxsb",
    "truncated": false,
    "entities": {
      "hashtags": [
        {
          "text": "vccomenta",
          "indices": [
            89,
            99
          ]
        }
      ],
      "symbols": [],
      "user_mentions": [
        {
          "screen_name": "globoesportecom",
          "name": "globoesportecom",
          "id": 10842792,
          "id_str": "10842792",
          "indices": [
            72,
            88
          ]
        }
      ],
      "urls": [
        {
          "url": "http://t.co/zHijqxsb",
          "expanded_url": "http://globoesporte.globo.com/temporeal/futebol/13-11-2011/corinthians-atletico-pr",
          "display_url": "globoesporte.globo.com/temporeal/fute…",
          "indices": [
            100,
            120
          ]
        }
      ]
    },
    "source": "<a href=\"https://dev.twitter.com/docs/tfw\" rel=\"nofollow\">Twitter for Websites</a>",
    "in_reply_to_status_id": null,
    "in_reply_to_status_id_str": null,
    "in_reply_to_user_id": null,
    "in_reply_to_user_id_str": null,
    "in_reply_to_screen_name": null,
    "user": {
      "id": 290283024,
      "id_str": "290283024",
      "name": "Ezequiel",
      "screen_name": "ZicaMessore",
      "location": "",
      "description": "",
      "url": null,
      "entities": {
        "description": {
          "urls": []
        }
      },
      "protected": false,
      "followers_count": 40,
      "friends_count": 139,
      "listed_count": 0,
      "created_at": "Sat Apr 30 01:29:24 +0000 2011",
      "favourites_count": 2,
      "utc_offset": null,
      "time_zone": null,
      "geo_enabled": true,
      "verified": false,
      "statuses_count": 21,
      "lang": "pt",
      "contributors_enabled": false,
      "is_translator": false,
      "is_translation_enabled": false,
      "profile_background_color": "642D8B",
      "profile_background_image_url": "http://abs.twimg.com/images/themes/theme10/bg.gif",
      "profile_background_image_url_https": "https://abs.twimg.com/images/themes/theme10/bg.gif",
      "profile_background_tile": true,
      "profile_image_url": "http://pbs.twimg.com/profile_images/838732277140062213/6HvND1Iy_normal.jpg",
      "profile_image_url_https": "https://pbs.twimg.com/profile_images/838732277140062213/6HvND1Iy_normal.jpg",
      "profile_link_color": "FF0000",
      "profile_sidebar_border_color": "65B0DA",
      "profile_sidebar_fill_color": "7AC3EE",
      "profile_text_color": "3D1957",
      "profile_use_background_image": true,
      "has_extended_profile": false,
      "default_profile": false,
      "default_profile_image": false,
      "following": null,
      "follow_request_sent": null,
      "notifications": null,
      "translator_type": "none"
    },
    "geo": null,
    "coordinates": null,
    "place": null,
    "contributors": null,
    "is_quote_status": false,
    "retweet_count": 0,
    "favorite_count": 0,
    "favorited": false,
    "retweeted": false,
    "possibly_sensitive": false,
    "lang": "pt"
  },
  {
    "created_at": "Sun Oct 30 22:52:57 +0000 2011",
    "id": 130779248855236608,
    "id_str": "130779248855236608",
    "text": "De volta a liderança ... :-) Eh isso aii CORINTHIANS",
    "truncated": false,
    "entities": {
      "hashtags": [],
      "symbols": [],
      "user_mentions": [],
      "urls": []
    },
    "source": "<a href=\"http://twitter.com/download/android\" rel=\"nofollow\">Twitter for Android</a>",
    "in_reply_to_status_id": null,
    "in_reply_to_status_id_str": null,
    "in_reply_to_user_id": null,
    "in_reply_to_user_id_str": null,
    "in_reply_to_screen_name": null,
    "user": {
      "id": 290283024,
      "id_str": "290283024",
      "name": "Ezequiel",
      "screen_name": "ZicaMessore",
      "location": "",
      "description": "",
      "url": null,
      "entities": {
        "description": {
          "urls": []
        }
      },
      "protected": false,
      "followers_count": 40,
      "friends_count": 139,
      "listed_count": 0,
      "created_at": "Sat Apr 30 01:29:24 +0000 2011",
      "favourites_count": 2,
      "utc_offset": null,
      "time_zone": null,
      "geo_enabled": true,
      "verified": false,
      "statuses_count": 21,
      "lang": "pt",
      "contributors_enabled": false,
      "is_translator": false,
      "is_translation_enabled": false,
      "profile_background_color": "642D8B",
      "profile_background_image_url": "http://abs.twimg.com/images/themes/theme10/bg.gif",
      "profile_background_image_url_https": "https://abs.twimg.com/images/themes/theme10/bg.gif",
      "profile_background_tile": true,
      "profile_image_url": "http://pbs.twimg.com/profile_images/838732277140062213/6HvND1Iy_normal.jpg",
      "profile_image_url_https": "https://pbs.twimg.com/profile_images/838732277140062213/6HvND1Iy_normal.jpg",
      "profile_link_color": "FF0000",
      "profile_sidebar_border_color": "65B0DA",
      "profile_sidebar_fill_color": "7AC3EE",
      "profile_text_color": "3D1957",
      "profile_use_background_image": true,
      "has_extended_profile": false,
      "default_profile": false,
      "default_profile_image": false,
      "following": null,
      "follow_request_sent": null,
      "notifications": null,
      "translator_type": "none"
    },
    "geo": null,
    "coordinates": null,
    "place": null,
    "contributors": null,
    "is_quote_status": false,
    "retweet_count": 0,
    "favorite_count": 0,
    "favorited": false,
    "retweeted": false,
    "lang": "pt"
  },
  {
    "created_at": "Fri Oct 28 13:26:13 +0000 2011",
    "id": 129911848597336064,
    "id_str": "129911848597336064",
    "text": "Oppa fds chegando agora  soh eh soh ver pra onde nois vaii....",
    "truncated": false,
    "entities": {
      "hashtags": [],
      "symbols": [],
      "user_mentions": [],
      "urls": []
    },
    "source": "<a href=\"http://twitter.com/download/android\" rel=\"nofollow\">Twitter for Android</a>",
    "in_reply_to_status_id": null,
    "in_reply_to_status_id_str": null,
    "in_reply_to_user_id": null,
    "in_reply_to_user_id_str": null,
    "in_reply_to_screen_name": null,
    "user": {
      "id": 290283024,
      "id_str": "290283024",
      "name": "Ezequiel",
      "screen_name": "ZicaMessore",
      "location": "",
      "description": "",
      "url": null,
      "entities": {
        "description": {
          "urls": []
        }
      },
      "protected": false,
      "followers_count": 40,
      "friends_count": 139,
      "listed_count": 0,
      "created_at": "Sat Apr 30 01:29:24 +0000 2011",
      "favourites_count": 2,
      "utc_offset": null,
      "time_zone": null,
      "geo_enabled": true,
      "verified": false,
      "statuses_count": 21,
      "lang": "pt",
      "contributors_enabled": false,
      "is_translator": false,
      "is_translation_enabled": false,
      "profile_background_color": "642D8B",
      "profile_background_image_url": "http://abs.twimg.com/images/themes/theme10/bg.gif",
      "profile_background_image_url_https": "https://abs.twimg.com/images/themes/theme10/bg.gif",
      "profile_background_tile": true,
      "profile_image_url": "http://pbs.twimg.com/profile_images/838732277140062213/6HvND1Iy_normal.jpg",
      "profile_image_url_https": "https://pbs.twimg.com/profile_images/838732277140062213/6HvND1Iy_normal.jpg",
      "profile_link_color": "FF0000",
      "profile_sidebar_border_color": "65B0DA",
      "profile_sidebar_fill_color": "7AC3EE",
      "profile_text_color": "3D1957",
      "profile_use_background_image": true,
      "has_extended_profile": false,
      "default_profile": false,
      "default_profile_image": false,
      "following": null,
      "follow_request_sent": null,
      "notifications": null,
      "translator_type": "none"
    },
    "geo": null,
    "coordinates": null,
    "place": null,
    "contributors": null,
    "is_quote_status": false,
    "retweet_count": 0,
    "favorite_count": 0,
    "favorited": false,
    "retweeted": false,
    "lang": "pt"
  },
  {
    "created_at": "Thu Sep 15 01:06:37 +0000 2011",
    "id": 114143044365852672,
    "id_str": "114143044365852672",
    "text": "Vamos Hermanos ... \nVamos Lá q ta perto",
    "truncated": false,
    "entities": {
      "hashtags": [],
      "symbols": [],
      "user_mentions": [],
      "urls": []
    },
    "source": "<a href=\"http://twitter.com\" rel=\"nofollow\">Twitter Web Client</a>",
    "in_reply_to_status_id": null,
    "in_reply_to_status_id_str": null,
    "in_reply_to_user_id": null,
    "in_reply_to_user_id_str": null,
    "in_reply_to_screen_name": null,
    "user": {
      "id": 290283024,
      "id_str": "290283024",
      "name": "Ezequiel",
      "screen_name": "ZicaMessore",
      "location": "",
      "description": "",
      "url": null,
      "entities": {
        "description": {
          "urls": []
        }
      },
      "protected": false,
      "followers_count": 40,
      "friends_count": 139,
      "listed_count": 0,
      "created_at": "Sat Apr 30 01:29:24 +0000 2011",
      "favourites_count": 2,
      "utc_offset": null,
      "time_zone": null,
      "geo_enabled": true,
      "verified": false,
      "statuses_count": 21,
      "lang": "pt",
      "contributors_enabled": false,
      "is_translator": false,
      "is_translation_enabled": false,
      "profile_background_color": "642D8B",
      "profile_background_image_url": "http://abs.twimg.com/images/themes/theme10/bg.gif",
      "profile_background_image_url_https": "https://abs.twimg.com/images/themes/theme10/bg.gif",
      "profile_background_tile": true,
      "profile_image_url": "http://pbs.twimg.com/profile_images/838732277140062213/6HvND1Iy_normal.jpg",
      "profile_image_url_https": "https://pbs.twimg.com/profile_images/838732277140062213/6HvND1Iy_normal.jpg",
      "profile_link_color": "FF0000",
      "profile_sidebar_border_color": "65B0DA",
      "profile_sidebar_fill_color": "7AC3EE",
      "profile_text_color": "3D1957",
      "profile_use_background_image": true,
      "has_extended_profile": false,
      "default_profile": false,
      "default_profile_image": false,
      "following": null,
      "follow_request_sent": null,
      "notifications": null,
      "translator_type": "none"
    },
    "geo": null,
    "coordinates": null,
    "place": null,
    "contributors": null,
    "is_quote_status": false,
    "retweet_count": 0,
    "favorite_count": 0,
    "favorited": false,
    "retweeted": false,
    "lang": "es"
  },
  {
    "created_at": "Sun Aug 28 15:41:39 +0000 2011",
    "id": 107840275522658304,
    "id_str": "107840275522658304",
    "text": "VaiManchester .... @espnagora",
    "truncated": false,
    "entities": {
      "hashtags": [],
      "symbols": [],
      "user_mentions": [
        {
          "screen_name": "ESPNagora",
          "name": "Mundo ESPN",
          "id": 51124892,
          "id_str": "51124892",
          "indices": [
            19,
            29
          ]
        }
      ],
      "urls": []
    },
    "source": "<a href=\"http://twitter.com\" rel=\"nofollow\">Twitter Web Client</a>",
    "in_reply_to_status_id": null,
    "in_reply_to_status_id_str": null,
    "in_reply_to_user_id": null,
    "in_reply_to_user_id_str": null,
    "in_reply_to_screen_name": null,
    "user": {
      "id": 290283024,
      "id_str": "290283024",
      "name": "Ezequiel",
      "screen_name": "ZicaMessore",
      "location": "",
      "description": "",
      "url": null,
      "entities": {
        "description": {
          "urls": []
        }
      },
      "protected": false,
      "followers_count": 40,
      "friends_count": 139,
      "listed_count": 0,
      "created_at": "Sat Apr 30 01:29:24 +0000 2011",
      "favourites_count": 2,
      "utc_offset": null,
      "time_zone": null,
      "geo_enabled": true,
      "verified": false,
      "statuses_count": 21,
      "lang": "pt",
      "contributors_enabled": false,
      "is_translator": false,
      "is_translation_enabled": false,
      "profile_background_color": "642D8B",
      "profile_background_image_url": "http://abs.twimg.com/images/themes/theme10/bg.gif",
      "profile_background_image_url_https": "https://abs.twimg.com/images/themes/theme10/bg.gif",
      "profile_background_tile": true,
      "profile_image_url": "http://pbs.twimg.com/profile_images/838732277140062213/6HvND1Iy_normal.jpg",
      "profile_image_url_https": "https://pbs.twimg.com/profile_images/838732277140062213/6HvND1Iy_normal.jpg",
      "profile_link_color": "FF0000",
      "profile_sidebar_border_color": "65B0DA",
      "profile_sidebar_fill_color": "7AC3EE",
      "profile_text_color": "3D1957",
      "profile_use_background_image": true,
      "has_extended_profile": false,
      "default_profile": false,
      "default_profile_image": false,
      "following": null,
      "follow_request_sent": null,
      "notifications": null,
      "translator_type": "none"
    },
    "geo": null,
    "coordinates": null,
    "place": null,
    "contributors": null,
    "is_quote_status": false,
    "retweet_count": 0,
    "favorite_count": 0,
    "favorited": false,
    "retweeted": false,
    "lang": "fr"
  },
  {
    "created_at": "Thu Aug 04 00:00:30 +0000 2011",
    "id": 98906116427223040,
    "id_str": "98906116427223040",
    "text": "Goool  Vai PRa SIMA =)",
    "truncated": false,
    "entities": {
      "hashtags": [],
      "symbols": [],
      "user_mentions": [],
      "urls": []
    },
    "source": "<a href=\"http://twitter.com\" rel=\"nofollow\">Twitter Web Client</a>",
    "in_reply_to_status_id": null,
    "in_reply_to_status_id_str": null,
    "in_reply_to_user_id": null,
    "in_reply_to_user_id_str": null,
    "in_reply_to_screen_name": null,
    "user": {
      "id": 290283024,
      "id_str": "290283024",
      "name": "Ezequiel",
      "screen_name": "ZicaMessore",
      "location": "",
      "description": "",
      "url": null,
      "entities": {
        "description": {
          "urls": []
        }
      },
      "protected": false,
      "followers_count": 40,
      "friends_count": 139,
      "listed_count": 0,
      "created_at": "Sat Apr 30 01:29:24 +0000 2011",
      "favourites_count": 2,
      "utc_offset": null,
      "time_zone": null,
      "geo_enabled": true,
      "verified": false,
      "statuses_count": 21,
      "lang": "pt",
      "contributors_enabled": false,
      "is_translator": false,
      "is_translation_enabled": false,
      "profile_background_color": "642D8B",
      "profile_background_image_url": "http://abs.twimg.com/images/themes/theme10/bg.gif",
      "profile_background_image_url_https": "https://abs.twimg.com/images/themes/theme10/bg.gif",
      "profile_background_tile": true,
      "profile_image_url": "http://pbs.twimg.com/profile_images/838732277140062213/6HvND1Iy_normal.jpg",
      "profile_image_url_https": "https://pbs.twimg.com/profile_images/838732277140062213/6HvND1Iy_normal.jpg",
      "profile_link_color": "FF0000",
      "profile_sidebar_border_color": "65B0DA",
      "profile_sidebar_fill_color": "7AC3EE",
      "profile_text_color": "3D1957",
      "profile_use_background_image": true,
      "has_extended_profile": false,
      "default_profile": false,
      "default_profile_image": false,
      "following": null,
      "follow_request_sent": null,
      "notifications": null,
      "translator_type": "none"
    },
    "geo": null,
    "coordinates": null,
    "place": null,
    "contributors": null,
    "is_quote_status": false,
    "retweet_count": 0,
    "favorite_count": 0,
    "favorited": false,
    "retweeted": false,
    "lang": "pt"
  }
]